Metadata-Version: 2.1
Name: psvg-cli
Version: 0.1
Summary: Apply transformations to Parametric SVG files
Home-page: https://github.com/jamesscottbrown/psvg-cli
Author: James Scott-Brown
Author-email: james@jamesscottbrown.com
License: Apache License, Version 2.0
Project-URL: Source, https://github.com/jamesscottbrown/psvg-cli
Project-URL: Issues, https://github.com/jamesscottbrown/psvg-cli/issues
Platform: UNKNOWN
Provides-Extra: test
